setup.cfg
setup.py
brokerest/__init__.py
brokerest/base.py
brokerest/errors.py
brokerest.egg-info/PKG-INFO
brokerest.egg-info/SOURCES.txt
brokerest.egg-info/dependency_links.txt
brokerest.egg-info/not-zip-safe
brokerest.egg-info/requires.txt
brokerest.egg-info/top_level.txt
brokerest/resources/__init__.py
brokerest/resources/restless.py