Metadata-Version: 1.0
Name: brokerest
Version: 0.1.9
Summary: Python REST API client
Home-page: https://github.com/satrails/brokerest
Author: Jonathon Morgan, Wiktor Wojcikowski
Author-email: jonathon@satrails.com
License: MIT
Platform: UNKNOWN
